mt/gpu/__init__.py
mt/gpu/arch.py
mt/gpu/arch_amd64_amd.py
mt/gpu/arch_amd64_cpu.py
mt/gpu/arch_amd64_nvidia.py
mt/gpu/arch_rock.py
mt/gpu/arch_rpi.py
mt/gpu/arch_tegra.py
mt/gpu/version.py
mtgpu-0.10.4.data/scripts/detect_machine
mtgpu-0.10.4.dist-info/licenses/LICENSE
mtgpu-0.10.4.dist-info/METADATA
mtgpu-0.10.4.dist-info/WHEEL
mtgpu-0.10.4.dist-info/top_level.txt
mtgpu-0.10.4.dist-info/RECORD
