Metadata-Version: 2.4
Name: mtgpu
Version: 0.10.4
Summary: Minh-Tri Pham's approach to detect gpu capacity
Home-page: https://github.com/inteplus/mtgpu
Author: ['Minh-Tri Pham']
Project-URL: Documentation, https://mtdoc.readthedocs.io/en/latest/mt.gpu/mt.gpu.html
Project-URL: Source Code, https://github.com/inteplus/mtgpu
License-File: LICENSE
Requires-Dist: psutil
Requires-Dist: tqdm
Dynamic: author
Dynamic: home-page
Dynamic: license-file
Dynamic: project-url
Dynamic: requires-dist
Dynamic: summary
